motherjokes/__init__.py
motherjokes/__version__.py
motherjokes/mother_jokes.py
motherjokes-0.1.2.dist-info/LICENSE
motherjokes-0.1.2.dist-info/METADATA
motherjokes-0.1.2.dist-info/WHEEL
motherjokes-0.1.2.dist-info/top_level.txt
motherjokes-0.1.2.dist-info/RECORD
