Metadata-Version: 2.1
Name: motherjokes
Version: 0.1.2
Summary: Transform sentences into awesome jokes about your mother (in russian language for now)
Home-page: https://github.com/FFFEGO/motherjokes
Author: Vladimir Kaigorodov
Author-email: vladimir.kgrdv@gmail.com
License: MIT
Platform: UNKNOWN
Classifier: License :: OSI Approved :: MIT License
Classifier: Programming Language :: Python
Classifier: Programming Language :: Python :: 3
Classifier: Programming Language :: Python :: 3.6
Classifier: Programming Language :: Python :: 3.7
Classifier: Topic :: Text Processing :: Linguistic
Requires-Python: >=3.6
Requires-Dist: pymorphy2 (==0.8)
Requires-Dist: mosestokenizer (==1.0.0)
Provides-Extra: dev
Requires-Dist: black ; extra == 'dev'
Requires-Dist: pylint ; extra == 'dev'
Requires-Dist: pytest ; extra == 'dev'
Requires-Dist: pytest-cov ; extra == 'dev'
Requires-Dist: coveralls ; extra == 'dev'
